vasudha/__init__.py
vasudha-0.0.1.dist-info/METADATA
vasudha-0.0.1.dist-info/WHEEL
vasudha-0.0.1.dist-info/top_level.txt
vasudha-0.0.1.dist-info/RECORD
