Metadata-Version: 2.4
Name: vasudha
Version: 0.0.1
Summary: Dummy lock package for vasudha
Author: AutoPublisher
